[
  {
    "full_name": "LLK/scratch-www",
    "stargazers_count": 1311,
    "open_issues_count": 596,
    "forks_count": 672
  },
  {
    "full_name": "dkundel/create-project",
    "stargazers_count": 98,
    "open_issues_count": 4,
    "forks_count": 29
  },
  {
    "full_name": "TwilioDevEd/browser-calls-csharp",
    "stargazers_count": 11,
    "open_issues_count": 29,
    "forks_count": 10
  },
  {
    "full_name": "twilio-labs/code-exchange",
    "stargazers_count": 22,
    "open_issues_count": 29,
    "forks_count": 14
  },
  {
    "full_name": "TwilioDevEd/browser-calls-node",
    "stargazers_count": 58,
    "open_issues_count": 21,
    "forks_count": 37
  },
  {
    "full_name": "TwilioDevEd/api-snippets",
    "stargazers_count": 221,
    "open_issues_count": 60,
    "forks_count": 423
  },
  {
    "full_name": "philnash/ngrok-for-vscode",
    "stargazers_count": 89,
    "open_issues_count": 8,
    "forks_count": 8
  },
  {
    "full_name": "Submitty/Submitty",
    "stargazers_count": 343,
    "open_issues_count": 405,
    "forks_count": 292
  },
  {
    "full_name": "WarenGonzaga/gathertown.js",
    "stargazers_count": 10,
    "open_issues_count": 4,
    "forks_count": 4
  },
  {
    "full_name": "PipedreamHQ/pipedream",
    "stargazers_count": 2215,
    "open_issues_count": 582,
    "forks_count": 1440
  },
  {
    "full_name": "cweems/twilio-keyword",
    "stargazers_count": 1,
    "open_issues_count": 1,
    "forks_count": 0
  },
  {
    "full_name": "kclejeune/TMobile-ISP-Client",
    "stargazers_count": 23,
    "open_issues_count": 6,
    "forks_count": 3
  },
  {
    "full_name": "twilio-labs/function-templates",
    "stargazers_count": 193,
    "open_issues_count": 36,
    "forks_count": 188
  }
]